uq_physicell/LICENSE.md
uq_physicell/VERSION.py
uq_physicell/__init__.py
uq_physicell/pc_model.py
uq_physicell/abc/__init__.py
uq_physicell/abc/abc_context.py
uq_physicell/bo/__init__.py
uq_physicell/bo/bo_context.py
uq_physicell/bo/plots.py
uq_physicell/bo/utils.py
uq_physicell/database/__init__.py
uq_physicell/database/bo_db.py
uq_physicell/database/ma_db.py
uq_physicell/database/utils.py
uq_physicell/doc/icon.png
uq_physicell/gui/load_files.py
uq_physicell/gui/main_window.py
uq_physicell/gui/tab1_select_params.py
uq_physicell/gui/tab2_model_analysis.py
uq_physicell/gui/tab3_calibration.py
uq_physicell/gui/tab4_model_selection.py
uq_physicell/model_analysis/__init__.py
uq_physicell/model_analysis/ma_context.py
uq_physicell/model_analysis/samplers.py
uq_physicell/model_analysis/sensitivity_analysis.py
uq_physicell/model_analysis/utils.py
uq_physicell/utils/__init__.py
uq_physicell/utils/distances.py
uq_physicell/utils/model_wrapper.py
uq_physicell/utils/sumstats.py
uq_physicell-1.2.4.dist-info/METADATA
uq_physicell-1.2.4.dist-info/WHEEL
uq_physicell-1.2.4.dist-info/entry_points.txt
uq_physicell-1.2.4.dist-info/RECORD
