Metadata-Version: 2.4
Name: uq_physicell
Version: 1.2.4
Summary: Project to perform uncertainty quantification of PhysiCell models
Project-URL: Homepage, https://github.com/heberlr/UQ_PhysiCell
Author-email: "Heber L. Rocha" <heberonly@gmail.com>
License: BSD 3-Clause License
Keywords: Calibration,Model selection,PhysiCell,Sensitivity Analysis,Uncertainty Quantification
Requires-Python: >=3.10
Requires-Dist: pcdl
Requires-Dist: salib
Provides-Extra: abc
Requires-Dist: pyabc; extra == 'abc'
Provides-Extra: bo
Requires-Dist: botorch; extra == 'bo'
Requires-Dist: gpytorch; extra == 'bo'
Requires-Dist: torch; extra == 'bo'
Provides-Extra: docs
Requires-Dist: linkify-it-py>=2.0; extra == 'docs'
Requires-Dist: myst-parser>=0.18; extra == 'docs'
Requires-Dist: sphinx-autobuild>=2021.3.14; extra == 'docs'
Requires-Dist: sphinx-rtd-theme>=1.0; extra == 'docs'
Requires-Dist: sphinx>=5.0; extra == 'docs'
